3rdpartylicenses.txt
hpc_acm_cli/.hpc_acm_cli_config
hpc_acm_cli/3rdpartylicenses.txt
hpc_acm_cli/__init__.py
hpc_acm_cli/aad.py
hpc_acm_cli/async_op.py
hpc_acm_cli/clus.py
hpc_acm_cli/command.py
hpc_acm_cli/diag.py
hpc_acm_cli/easy_config.py
hpc_acm_cli/main.py
hpc_acm_cli/main_async.py
hpc_acm_cli/node.py
hpc_acm_cli/parser_builder.py
hpc_acm_cli/utils.py
hpc_acm_cli-2.8.4.dist-info/DESCRIPTION.rst
hpc_acm_cli-2.8.4.dist-info/METADATA
hpc_acm_cli-2.8.4.dist-info/RECORD
hpc_acm_cli-2.8.4.dist-info/WHEEL
hpc_acm_cli-2.8.4.dist-info/entry_points.txt
hpc_acm_cli-2.8.4.dist-info/metadata.json
hpc_acm_cli-2.8.4.dist-info/top_level.txt
