Metadata-Version: 2.0
Name: hpc-acm-cli
Version: 2.8.4
Summary: HPC ACM Client
Home-page: https://github.com/Azure/hpcpack-acm-cli
Author: Microsoft HPC Pack
Author-email: hpccoree@microsoft.com
License: UNKNOWN
Platform: UNKNOWN
Classifier: Programming Language :: Python :: 2
Classifier: Programming Language :: Python :: 2.7
Classifier: Programming Language :: Python :: 3
Classifier: Programming Language :: Python :: 3.5
Classifier: Programming Language :: Python :: 3.6
Classifier: License :: OSI Approved :: MIT License
Classifier: Operating System :: OS Independent
Requires-Dist: hpc-acm (>=1.3.0)
Requires-Dist: terminaltables (>=3.1.0)
Requires-Dist: tqdm (>=4.24.0)
Requires-Dist: adal (>=1.2.0)
